[
    {
        "header":"Javascript Quiz",
        "imageref":"./projectImages/javascriptQuiz.webp",
        "gitRef":"https://github.com/LaurenWollaston/Javascript-quiz",
        "projectRef":"https://laurenwollaston.github.io/Javascript-quiz/"
    },
    {
        "header":"Workday Scheduler",
        "imageref":"./projectImages/workdayscheduler.webp",
        "gitRef":"https://github.com/LaurenWollaston/Work-Day-Scheduler",
        "projectRef":"https://laurenwollaston.github.io/Work-Day-Scheduler/"
    },
    {
        "header":"Weather Report",
        "imageref":"./projectImages/weather.webp",
        "gitRef":"https://github.com/LaurenWollaston/Module6-WeatherAPI",
        "projectRef":"https://laurenwollaston.github.io/Module6-WeatherAPI/"
    },
    {
        "header":"Bottomfeeder",
        "imageref":"./projectImages/bottomfeeder.webp",
        "gitRef":"https://github.com/chartok/Bottom-Feeders",
        "projectRef":"https://chartok.github.io/Bottom-Feeders/"
    }
]